raiderio/__init__.py
raiderio/api.py
raiderio-1.1.1.dist-info/METADATA
raiderio-1.1.1.dist-info/WHEEL
raiderio-1.1.1.dist-info/top_level.txt
raiderio-1.1.1.dist-info/RECORD
